mategenair/__init__.py
mategenair/_version.py
mategenair-0.2.2.data/data/share/jupyter/labextensions/mategenair/build_log.json
mategenair-0.2.2.data/data/share/jupyter/labextensions/mategenair/package.json
mategenair-0.2.2.data/data/share/jupyter/labextensions/mategenair/static/934aca7d3f24ac6b8dbd.svg
mategenair-0.2.2.data/data/share/jupyter/labextensions/mategenair/static/9591665ae5747407f855.svg
mategenair-0.2.2.data/data/share/jupyter/labextensions/mategenair/static/e3a91996c625df47ce7a.png
mategenair-0.2.2.data/data/share/jupyter/labextensions/mategenair/static/lib_index_js.15f1ea87f3faaddb19f2.js
mategenair-0.2.2.data/data/share/jupyter/labextensions/mategenair/static/lib_index_js.15f1ea87f3faaddb19f2.js.map
mategenair-0.2.2.data/data/share/jupyter/labextensions/mategenair/static/node_modules_marked-highlight_src_index_js.19b1113de165e8410352.js
mategenair-0.2.2.data/data/share/jupyter/labextensions/mategenair/static/node_modules_marked-highlight_src_index_js.19b1113de165e8410352.js.map
mategenair-0.2.2.data/data/share/jupyter/labextensions/mategenair/static/remoteEntry.5ee77b1edf058a7505f0.js
mategenair-0.2.2.data/data/share/jupyter/labextensions/mategenair/static/remoteEntry.5ee77b1edf058a7505f0.js.map
mategenair-0.2.2.data/data/share/jupyter/labextensions/mategenair/static/style.js
mategenair-0.2.2.data/data/share/jupyter/labextensions/mategenair/static/style_index_js.604ea4abf3d6d0f2af86.js
mategenair-0.2.2.data/data/share/jupyter/labextensions/mategenair/static/style_index_js.604ea4abf3d6d0f2af86.js.map
mategenair-0.2.2.data/data/share/jupyter/labextensions/mategenair/static/vendors-node_modules_dompurify_dist_purify_js.61969b5c0ceb0c67c5ad.js
mategenair-0.2.2.data/data/share/jupyter/labextensions/mategenair/static/vendors-node_modules_dompurify_dist_purify_js.61969b5c0ceb0c67c5ad.js.map
mategenair-0.2.2.data/data/share/jupyter/labextensions/mategenair/static/vendors-node_modules_gsap_index_js.d1bf59c0f9cd87b7e950.js
mategenair-0.2.2.dist-info/METADATA
mategenair-0.2.2.dist-info/WHEEL
mategenair-0.2.2.dist-info/licenses/LICENSE
mategenair-0.2.2.dist-info/RECORD
